README.rst
setup.py
hue/__init__.py
hue/hue.py
hue.egg-info/PKG-INFO
hue.egg-info/SOURCES.txt
hue.egg-info/dependency_links.txt
hue.egg-info/pbr.json
hue.egg-info/requires.txt
hue.egg-info/top_level.txt