Metadata-Version: 1.0
Name: hue
Version: 0.1.0
Summary: Python client for Philips Hue
Home-page: https://github.com/issackelly/python-hue
Author: Issac Kelly
Author-email: issac.kelly@gmail.com
License: MIT
Keywords: phillips hue,client
Platform: UNKNOWN
